numba_stats/__init__.py
numba_stats/_special.py
numba_stats/_util.py
numba_stats/argus.py
numba_stats/bernstein.py
numba_stats/binom.py
numba_stats/cmsshape.py
numba_stats/cpoisson.py
numba_stats/cruijff.py
numba_stats/crystalball.py
numba_stats/crystalball_ex.py
numba_stats/expon.py
numba_stats/laplace.py
numba_stats/lognorm.py
numba_stats/norm.py
numba_stats/poisson.py
numba_stats/qgaussian.py
numba_stats/t.py
numba_stats/truncexpon.py
numba_stats/truncnorm.py
numba_stats/tsallis.py
numba_stats/uniform.py
numba_stats/voigt.py
numba_stats-1.11.0.dist-info/licenses/LICENSE
numba_stats-1.11.0.dist-info/METADATA
numba_stats-1.11.0.dist-info/WHEEL
numba_stats-1.11.0.dist-info/top_level.txt
numba_stats-1.11.0.dist-info/RECORD
