Metadata-Version: 2.4
Name: numba-stats
Version: 1.11.0
Summary: Numba-accelerated implementations of scipy probability distributions and others used in particle physics
Author-email: Hans Dembinski <hans.dembinski@gmail.com>
License: MIT
Project-URL: repository, https://github.com/hdembinski/numba-stats
Classifier: Development Status :: 5 - Production/Stable
Classifier: Intended Audience :: Science/Research
Classifier: License :: OSI Approved :: MIT License
Classifier: Operating System :: OS Independent
Classifier: Programming Language :: Python :: 3
Classifier: Programming Language :: Python :: 3
Classifier: Programming Language :: Python :: 3 :: Only
Classifier: Programming Language :: Python :: 3.9
Classifier: Programming Language :: Python :: 3.10
Classifier: Programming Language :: Python :: 3.11
Classifier: Programming Language :: Python :: 3.12
Classifier: Programming Language :: Python :: Implementation :: CPython
Requires-Python: >=3.9
License-File: LICENSE
Requires-Dist: numba>=0.53
Requires-Dist: numpy>=1.20
Requires-Dist: scipy>=1.5
Provides-Extra: test
Requires-Dist: pytest>=6; extra == "test"
Requires-Dist: pytest-cov>=5; extra == "test"
Requires-Dist: pytest-benchmark>=4; extra == "test"
Requires-Dist: pydocstyle>=6; extra == "test"
Requires-Dist: coverage>=6; extra == "test"
Requires-Dist: nox; extra == "test"
Dynamic: license-file
